nesterWhz.py
setup.py
nesterWhz.egg-info/PKG-INFO
nesterWhz.egg-info/SOURCES.txt
nesterWhz.egg-info/dependency_links.txt
nesterWhz.egg-info/top_level.txt