Metadata-Version: 1.0
Name: nesterWhz
Version: 1.0
Summary: test nesterWhz
Home-page: http://www.baidu.com
Author: whz
Author-email: 1217044974@qq.com
License: UNKNOWN
Platform: UNKNOWN
